COPYING
MANIFEST.in
README.rst
requirements.txt
setup.py
beancount/VERSION
beancount/__init__.py
beancount/loader.py
beancount/loader_test.py
beancount/core/__init__.py
beancount/core/account.py
beancount/core/account_test.py
beancount/core/account_types.py
beancount/core/account_types_test.py
beancount/core/amount.py
beancount/core/amount_test.py
beancount/core/compare.py
beancount/core/compare_test.py
beancount/core/convert.py
beancount/core/convert_test.py
beancount/core/data.py
beancount/core/data_test.py
beancount/core/display_context.py
beancount/core/display_context_test.py
beancount/core/distribution.py
beancount/core/distribution_test.py
beancount/core/flags.py
beancount/core/flags_test.py
beancount/core/getters.py
beancount/core/getters_test.py
beancount/core/interpolate.py
beancount/core/interpolate_test.py
beancount/core/inventory.py
beancount/core/inventory_test.py
beancount/core/number.py
beancount/core/number_test.py
beancount/core/position.py
beancount/core/position_test.py
beancount/core/prices.py
beancount/core/prices_test.py
beancount/core/realization.py
beancount/core/realization_test.py
beancount/ingest/__init__.py
beancount/ingest/cache.py
beancount/ingest/cache_test.py
beancount/ingest/extract.py
beancount/ingest/extract_test.py
beancount/ingest/file.py
beancount/ingest/file_test.py
beancount/ingest/identify.py
beancount/ingest/identify_test.py
beancount/ingest/importer.py
beancount/ingest/importer_test.py
beancount/ingest/regression.py
beancount/ingest/regression_pytest.py
beancount/ingest/regression_test.py
beancount/ingest/scripts_utils.py
beancount/ingest/scripts_utils_test.py
beancount/ingest/similar.py
beancount/ingest/similar_test.py
beancount/ingest/importers/__init__.py
beancount/ingest/importers/config.py
beancount/ingest/importers/config_test.py
beancount/ingest/importers/csv.py
beancount/ingest/importers/csv_test.py
beancount/ingest/importers/fileonly.py
beancount/ingest/importers/fileonly_test.py
beancount/ingest/importers/ofx.py
g8fyi_beancount.egg-info/PKG-INFO
g8fyi_beancount.egg-info/SOURCES.txt
g8fyi_beancount.egg-info/dependency_links.txt
g8fyi_beancount.egg-info/entry_points.txt
g8fyi_beancount.egg-info/requires.txt
g8fyi_beancount.egg-info/top_level.txt