Metadata-Version: 2.1
Name: g8fyi-beancount
Version: 1.0.8
Summary: Command-line Double-Entry Accounting
Home-page: http://furius.ca/beancount
Download-URL: https://github.com/beancount/beancount
Author: Martin Blais
Author-email: blais@furius.ca
License: GNU GPLv2 only
Requires-Python: >=3.6
License-File: COPYING
